inhoj/__init__.py
inhoj/classes.py
inhoj/contexts.py
inhoj/funcs.py
inhoj/prints.py
inhoj/version.py
inhoj-2.1.2.dist-info/DESCRIPTION.rst
inhoj-2.1.2.dist-info/METADATA
inhoj-2.1.2.dist-info/RECORD
inhoj-2.1.2.dist-info/WHEEL
inhoj-2.1.2.dist-info/metadata.json
inhoj-2.1.2.dist-info/top_level.txt
