Metadata-Version: 2.0
Name: inhoj
Version: 2.1.2
Summary: Useful Python Code Snippets
Home-page: https://github.com/johnidm/inhoj
Author: Johni Douglas Marangon
Author-email: johni.douglas.marangon@gmail.com
License: MIT License
Keywords: inhoj
Platform: UNKNOWN
Classifier: Development Status :: 2 - Pre-Alpha
Classifier: Intended Audience :: Developers
Classifier: License :: OSI Approved :: MIT License
Classifier: Natural Language :: English
Classifier: Programming Language :: Python :: 3.5
